ezbar.py
ezbar-1.6.dist-info/LICENSE
ezbar-1.6.dist-info/METADATA
ezbar-1.6.dist-info/WHEEL
ezbar-1.6.dist-info/top_level.txt
ezbar-1.6.dist-info/RECORD
