Metadata-Version: 2.1
Name: ezbar
Version: 1.6
Summary: A simple progress bar for loop progress measurement and time estimation.
Author-email: Paulo Sanchez <dev.szblzpaulo@gmail.com>, Carlos Puente <carlospuenteg@gmail.com>
Project-URL: Homepage, https://github.com/erlete/simple-progress-bar
Project-URL: Bug Tracker, https://github.com/erlete/simple-progress-bar/issues
Classifier: Development Status :: 5 - Production/Stable
Classifier: Intended Audience :: Developers
Classifier: Programming Language :: Python :: 3
Classifier: License :: OSI Approved :: GNU General Public License v3 (GPLv3)
Classifier: Operating System :: MacOS
Classifier: Operating System :: Unix
Classifier: Operating System :: POSIX
Classifier: Topic :: Software Development :: User Interfaces
Requires-Python: >=3.7
License-File: LICENSE
